pyape/__init__.py
pyape/cli.py
pyape/client.py
pyape_cyd-0.2.0.dist-info/METADATA
pyape_cyd-0.2.0.dist-info/WHEEL
pyape_cyd-0.2.0.dist-info/entry_points.txt
pyape_cyd-0.2.0.dist-info/licenses/LICENSE.txt
pyape_cyd-0.2.0.dist-info/RECORD
