Metadata-Version: 2.4
Name: pyape-cyd
Version: 0.2.0
Summary: Python client and CLI for the APE REST API
Author-email: Cyber-Detect <team@cyber-detect.com>
License-Expression: MIT
License-File: LICENSE.txt
Requires-Python: >=3.8
Requires-Dist: pydantic==2.9.2
Requires-Dist: requests==2.32.3
Requires-Dist: typer==0.16.0
Requires-Dist: websocket-client==1.8.0
